README.md
setup.py
additionals/__init__.py
additionals/check_ip.py
additionals/client_descriptor.py
additionals/client_meta.py
additionals/decos.py
additionals/errors.py
additionals/settings.py
additionals/utils.py
client/__init__.py
client/add_contact.py
client/client.py
client/client_connection.py
client/client_database.py
client/client_gui.py
client/client_window.py
client/del_contact.py
client/login.py
client/login_fail.py
client/login_fail_window.py
client/login_reg_window.py
client_mess_is_that_joke.egg-info/PKG-INFO
client_mess_is_that_joke.egg-info/SOURCES.txt
client_mess_is_that_joke.egg-info/dependency_links.txt
client_mess_is_that_joke.egg-info/requires.txt
client_mess_is_that_joke.egg-info/top_level.txt
log/__init__.py
test/__init__.py
test/test_client.py
test/test_utils.py